DST2/DescriptiveReporting.py
DST2/MultiColumnsValidation.py
DST2/MultiFilesValidation.py
DST2/QA.py
DST2/Reporting.py
DST2/SingleColumnValidation.py
DST2/Vizualization.py
DST2/__init__.py
DST2/core_validations.py
DST2/data_loader.py
DST2/file_transformation.py
DST2/my_file.py
DST2/sandbox.py
DST2/sandbox_2.py
DST2-0.0.3.dist-info/METADATA
DST2-0.0.3.dist-info/WHEEL
DST2-0.0.3.dist-info/top_level.txt
DST2-0.0.3.dist-info/RECORD
