Metadata-Version: 2.1
Name: DST2
Version: 0.0.3
Summary: Perform QA between 2 dataframes
Home-page: https://github.com/Kienka/DST2
Author: Kienka Cromwell Kio
Author-email: kienka.kio@sustainalytics.com
License: UNKNOWN
Platform: UNKNOWN
Classifier: Development Status :: 3 - Alpha
Classifier: Programming Language :: Python :: 3
Classifier: License :: OSI Approved :: MIT License
Classifier: Operating System :: OS Independent
Requires-Dist: pandas
